polarcap/__init__.py
polarcap-0.1.0.dist-info/METADATA
polarcap-0.1.0.dist-info/WHEEL
polarcap-0.1.0.dist-info/RECORD
