Metadata-Version: 2.4
Name: polarcap
Version: 0.1.0
Summary: PCAP decoding module with first-class support for Polars DataFrames
Project-URL: Homepage, https://github.com/markassad/polarcap
Project-URL: Repository, https://github.com/markassad/polarcap
Author: Mark Assad
License: MIT
Keywords: dataframe,networking,packet-capture,pcap,polars
Classifier: Operating System :: OS Independent
Classifier: Programming Language :: Python :: 3
Requires-Python: >=3.9
